naxxatrapy/__init__.py
naxxatrapy/naxxatrapy.py
naxxatrapy/version.py
naxxatrapy-1.0.1.dist-info/LICENSE
naxxatrapy-1.0.1.dist-info/METADATA
naxxatrapy-1.0.1.dist-info/WHEEL
naxxatrapy-1.0.1.dist-info/top_level.txt
naxxatrapy-1.0.1.dist-info/RECORD
