Metadata-Version: 2.1
Name: naxxatrapy
Version: 1.0.1
Summary: Read the latest Real Python tutorials
Home-page: https://github.com/naxxatra/naxxatrapy
Author: Naxxatra Sciences
Author-email: contact@naxxatra.com
License: MIT
Platform: UNKNOWN
Classifier: License :: OSI Approved :: MIT License
Classifier: Programming Language :: Python :: 3
Classifier: Programming Language :: Python :: 3.7
